{
 "actions": [],
 "allow_rename": 1,
 "autoname": "field:plan",
 "creation": "2025-08-14 14:49:20.352129",
 "doctype": "DocType",
 "editable_grid": 1,
 "engine": "InnoDB",
 "field_order": [
  "plan",
  "code",
  "ifp_days"
 ],
 "fields": [
  {
   "fieldname": "plan",
   "fieldtype": "Data",
   "in_list_view": 1,
   "label": "Plan",
   "unique": 1
  },
  {
   "fieldname": "code",
   "fieldtype": "Data",
   "in_list_view": 1,
   "label": "Code"
  },
  {
   "fieldname": "ifp_days",
   "fieldtype": "Data",
   "in_list_view": 1,
   "label": "IFP Days"
  }
 ],
 "index_web_pages_for_search": 1,
 "istable": 1,
 "links": [],
 "modified": "2026-03-27 09:05:58.731285",
 "modified_by": "Administrator",
 "module": "Edp Online Vehicles",
 "name": "Plan Codes",
 "naming_rule": "By fieldname",
 "owner": "Administrator",
 "permissions": [],
 "row_format": "Dynamic",
 "sort_field": "modified",
 "sort_order": "DESC",
 "states": []
}